PyChromeDevTools/__init__.py
PyChromeDevTools-0.1.dist-info/DESCRIPTION.rst
PyChromeDevTools-0.1.dist-info/METADATA
PyChromeDevTools-0.1.dist-info/RECORD
PyChromeDevTools-0.1.dist-info/WHEEL
PyChromeDevTools-0.1.dist-info/metadata.json
PyChromeDevTools-0.1.dist-info/top_level.txt
