Metadata-Version: 2.0
Name: PyChromeDevTools
Version: 0.1
Summary: PyChromeDevTools : Interact with Google Chrome using the Chrome DevTools Protocol.
Home-page: https://github.com/marty90/PyChromeDevTools
Author: Martino Trevisan
Author-email: martino.trevisan@polito.it
License: Apache License 2.0
Download-URL: https://github.com/marty90/PyChromeDevTools/tarball/1.0.1
Platform: UNKNOWN
Requires-Dist: requests
Requires-Dist: websocket-client
